prog/__init__.py
prog/arguments.py
prog/db_set.py
prog/guide_prediction.py
prog/json_format.py
prog/list_editors.py
prog/mEdit.py
prog/medit_lib.py
prog/ncbi_cross_database.py
prog/offtarget_prediction.py
prog/scratch.py
py/__init__.py
py/annotate.py
py/aws_pull.py
py/clinVar_pull.py
py/dataH.py
py/featurization.py
py/fetchGuides.py
py/find_offtargets.py
py/gdrive_import.py
py/genome_seq_search.py
py/make_tables.py
py/omim2hgvs.py
py/process_genome.py
py/scoring.py
py/validate.py
smk/__init__.py
smk/config/__init__.py
smk/config/aws_download.yaml
smk/config/caspedia_ingest.yaml
smk/config/cluster.yaml
smk/config/guide_prediction_default_template.yaml
smk/config/guide_prediction_private_template.yaml
smk/config/hgvs_input.yaml
smk/config/id_convert.yaml
smk/config/medit_cluster.yaml
smk/config/medit_database.yaml
smk/config/medit_guide_pred.yaml
smk/config/medit_offtarget.yaml
smk/config/preprocessing_configuration.yaml
smk/envs/__init__.py
smk/envs/b_medit.yaml
smk/envs/casoff.yaml
smk/envs/clinvar_pull.yaml
smk/envs/gdown.yaml
smk/envs/gscan.yaml
smk/envs/medit.yaml
smk/envs/samtools.yaml
smk/envs/tabix.yaml
smk/envs/vcf.yaml
smk/pipelines/__init__.py
smk/pipelines/compression_routine.smk
smk/pipelines/filename_standardization.smk
smk/pipelines/guide_prediction.smk
smk/pipelines/offtarget_prediction.smk
smk/pipelines/vcf_processing.smk
smk/pipelines/py/__init__.py
smk/pipelines/py/aggregate_alt_genomes.py
smk/pipelines/py/annotate.py
smk/pipelines/py/aws_pull.py
smk/pipelines/py/build_casoff_input.py
smk/pipelines/py/build_casoff_output.py
smk/pipelines/py/build_casoff_scores.py
smk/pipelines/py/clinVar_pull.py
smk/pipelines/py/dataH.py
smk/pipelines/py/dataH_fromAPP.py
smk/pipelines/py/deepcas_models.py
smk/pipelines/py/fasta_chromosome_rename.py
smk/pipelines/py/featurization.py
smk/pipelines/py/fetchGuides.py
smk/pipelines/py/fetchGuides_fromAPP.py
smk/pipelines/py/find_offtargets.py
smk/pipelines/py/gdrive_import.py
smk/pipelines/py/genome_seq_search.py
meditability-0.8.dist-info/LICENSE
meditability-0.8.dist-info/METADATA
meditability-0.8.dist-info/WHEEL
meditability-0.8.dist-info/entry_points.txt
meditability-0.8.dist-info/top_level.txt
meditability-0.8.dist-info/RECORD
