Metadata-Version: 2.1
Name: meditability
Version: 0.8
Author: Daniel Bellieny, Taylor Hudson
Author-email: bellieny@berkeley.edu, thudson@berkeley.edu
Classifier: Development Status :: 3 - Alpha
Classifier: Intended Audience :: Developers
Classifier: Topic :: Software Development :: Build Tools
License-File: LICENSE
Requires-Dist: snakemake ~=7.32.4
Requires-Dist: pulp <2.8.0
Requires-Dist: pandas >=2.1.1
Requires-Dist: numpy ~=1.26.0
Requires-Dist: wrapt >=1.15.0
Requires-Dist: biopython >=1.81
Requires-Dist: pyyaml >=6.0
Requires-Dist: importlib-resources >=6.1.1
Requires-Dist: pytz >=2023.3
Requires-Dist: boto3 >=1.28.57
Requires-Dist: requests >=2.32.3
Requires-Dist: alive-progress >=3.1.5
Requires-Dist: xmltodict >=0.13.0
